pystematic/__init__.py
pystematic/core.py
pystematic/help_formatters.py
pystematic/parametric.py
pystematic/standard_plugin/__init__.py
pystematic/standard_plugin/standard_plugin.py
pystematic/standard_plugin/yaml_wrapper.py
pystematic-1.7.0.dist-info/LICENSE
pystematic-1.7.0.dist-info/METADATA
pystematic-1.7.0.dist-info/WHEEL
pystematic-1.7.0.dist-info/entry_points.txt
pystematic-1.7.0.dist-info/RECORD
