Metadata-Version: 2.3
Name: pystematic
Version: 1.7.0
Summary: A framework that helps you setup and run reproducible experiments in python.
License: MIT
Author: E.Valldor
Requires-Python: >=3.9,<4.0
Classifier: Development Status :: 5 - Production/Stable
Classifier: Intended Audience :: Science/Research
Classifier: License :: OSI Approved :: MIT License
Classifier: Operating System :: OS Independent
Classifier: Programming Language :: Python
Classifier: Programming Language :: Python :: 3
Classifier: Programming Language :: Python :: 3.9
Classifier: Programming Language :: Python :: 3.10
Classifier: Programming Language :: Python :: 3.11
Classifier: Programming Language :: Python :: 3.12
Classifier: Programming Language :: Python :: 3.13
Classifier: Topic :: Scientific/Engineering
Requires-Dist: PyYAML (>=6.0.2,<7.0.0)
Requires-Dist: importlib-metadata (>=8.7.0,<9.0.0)
Requires-Dist: rich (>=14.0.0,<15.0.0)
Requires-Dist: typing-extensions (>=4.14.0,<5.0.0)
Requires-Dist: wrapt (>=1.17.2,<2.0.0)
Project-URL: Documentation, https://pystematic.readthedocs.io
Project-URL: Repository, https://github.com/evalldor/pystematic
